easy_vc_dev/__init__.py
easy_vc_dev/cli.py
easy_vc_dev/commons.py
easy_vc_dev/const.py
easy_vc_dev/misc/HParams.py
easy_vc_dev/model/LightweightRVC_Synthesizer_nof0.py
easy_vc_dev/model/MultiPeriodDiscriminatorV2.py
easy_vc_dev/model/components/APNet2/APNet2Decoder.py
easy_vc_dev/model/components/PosteriorEncoder.py
easy_vc_dev/model/components/ResidualCouplingBlock.py
easy_vc_dev/model/components/TextEncoder768.py
easy_vc_dev/model/components/hifigan/HifiganDecoder.py
easy_vc_dev/model/discriminator_components/DiscriminatorP.py
easy_vc_dev/model/discriminator_components/DiscriminatorS.py
easy_vc_dev/model/modules/Flip.py
easy_vc_dev/model/modules/LayerNorm.py
easy_vc_dev/model/modules/ResidualCouplingLayer.py
easy_vc_dev/model/modules/WN.py
easy_vc_dev/model/modules/attentions.py
easy_vc_dev/onnx/LightweightRVC_Synthesizer_nof0_onnx.py
easy_vc_dev/onnx/export_onnx.py
easy_vc_dev/onnx/infer_with_onnx.py
easy_vc_dev/train/components/data_utils.py
easy_vc_dev/train/generate_data_loader.py
easy_vc_dev/train/generate_gpu_cache.py
easy_vc_dev/train/generate_train_components.py
easy_vc_dev/train/load_checkpoints.py
easy_vc_dev/train/losses.py
easy_vc_dev/train/save_checkpoint.py
easy_vc_dev/train/tensorboard_utils/plot_spectrogram_to_numpy.py
easy_vc_dev/train/tensorboard_utils/summarize.py
easy_vc_dev/train/train.py
easy_vc_dev/utils/Downloader.py
easy_vc_dev/utils/Slicer.py
easy_vc_dev/utils/download.py
easy_vc_dev/utils/extract_feature.py
easy_vc_dev/utils/generate_filelist.py
easy_vc_dev/utils/get_logger.py
easy_vc_dev/utils/load_audio.py
easy_vc_dev/utils/mel_processing.py
easy_vc_dev/utils/parseBoolArg.py
easy_vc_dev/utils/preprocess.py
easy_vc_dev/utils/whisper/assets/mel_filters.npz
easy_vc_dev/utils/whisper/audio.py
easy_vc_dev/utils/whisper/model.py
easy_vc_dev/utils/whisper/utils.py
easy_vc_dev/utils/whisper/whisper.py
easy_vc_dev/webIF/frontend/dist/assets/buymeacoffee.png
easy_vc_dev/webIF/frontend/dist/assets/icons/blank.png
easy_vc_dev-0.1.1.dist-info/METADATA
easy_vc_dev-0.1.1.dist-info/WHEEL
easy_vc_dev-0.1.1.dist-info/entry_points.txt
easy_vc_dev-0.1.1.dist-info/RECORD
