Metadata-Version: 2.1
Name: easy-vc-dev
Version: 0.1.1
Summary: 
Author: wok
Requires-Python: >=3.10,<3.13
Classifier: Programming Language :: Python :: 3
Classifier: Programming Language :: Python :: 3.10
Classifier: Programming Language :: Python :: 3.11
Requires-Dist: colab-easy-ui (>=0.1.107,<0.2.0)
Requires-Dist: ffmpeg-python (>=0.2.0,<0.3.0)
Requires-Dist: fire (>=0.5.0,<0.6.0)
Requires-Dist: librosa (>=0.10.1,<0.11.0)
Requires-Dist: matplotlib (>=3.8.2,<4.0.0)
Requires-Dist: numpy (>=1.26.3,<2.0.0)
Requires-Dist: onnxsim (>=0.4.35,<0.5.0)
Requires-Dist: portpicker (>=1.6.0,<2.0.0)
Requires-Dist: pyinstaller (>=6.3.0,<7.0.0)
Requires-Dist: resampy (>=0.4.2,<0.5.0)
Requires-Dist: scipy (>=1.11.4,<2.0.0)
Requires-Dist: simple-performance-timer (>=0.1.2,<0.2.0)
Requires-Dist: tensorboard (>=2.15.1,<3.0.0)
Requires-Dist: torch (>=2.1.2,<3.0.0)
Requires-Dist: torchaudio (>=2.1.2,<3.0.0)
Requires-Dist: tqdm (>=4.66.1,<5.0.0)
